{
  "aic:6565": {
    "text": "American Gothic is a 1930 oil painting on beaverboard by the American Regionalist artist Grant Wood, depicting a Midwestern farmer and his daughter standing in front of their Carpenter Gothic style home. It is one of the most famous American paintings of the 20th century and is frequently referenced in popular culture.",
    "source": "wikipedia",
    "url": "https://en.wikipedia.org/wiki/American_Gothic",
    "at": 1780158285079
  },
  "aic:10287": {
    "text": "In the midst of a lush forest, a naked nymph steps cautiously into a tranquil pool, as if hesitant to disturb the serene atmosphere. The soft, golden light and gentle brushstrokes used by François Boucher create a sense of intimacy and quiet contemplation. This work showcases Boucher's mastery of the Rococo style, characterized by its emphasis on delicate, natural forms and subtle color palette. The result is a dreamlike scene that invites the viewer to step into its peaceful world. The painting's beauty lies in its ability to evoke a sense of stillness and calm.",
    "source": "ai",
    "url": null,
    "at": 1780158313946
  }
}